[
  {
    "name": "breachforums-database",
    "source": "https://breachforums.jp/Forum-Databases?sortby=started\u0026order=desc\u0026datecut=9999\u0026prefix=0",
    "title": "https://www.womencup.fr",
    "author": "ldopanda2",
    "link": "https://breachforums.jp/Thread-DATABASE-https-www-womencup-fr",
    "detection-date": "2026-02-05T09:02:35.068Z",
    "timestamp": "2026-02-05T09:02:35.068Z",
    "thread-id": "Thread-DATABASE-https-www-womencup-fr",
    "link-hash": "7492325d4ade4d676403b3798b81d53f8cf6a678fb0b221e6eff5ed07ba34cd5"
  },
  {
    "name": "breachforums-combolists",
    "source": "https://breachforums.jp/Forum-Combolists?sortby=started\u0026order=desc\u0026datecut=9999\u0026prefix=0",
    "title": "❄️❄️ 3398x PREMIUM HOTMAIL HITS ❄️❄️",
    "author": "xdalpha",
    "link": "https://breachforums.jp/Thread-%E2%9D%84%EF%B8%8F%E2%9D%84%EF%B8%8F-3398x-PREMIUM-HOTMAIL-HITS-%E2%9D%84%EF%B8%8F%E2%9D%84%EF%B8%8F",
    "detection-date": "2026-02-05T09:02:35.116Z",
    "timestamp": "2026-02-05T09:02:35.116Z",
    "thread-id": "",
    "link-hash": "8c081716f634b045e437fd26a72fcd835fcc378a5adc030c2c5e891aaae01dc8"
  },
  {
    "name": "breachforums-cracked-accounts",
    "source": "https://breachforums.jp/Forum-Cracked-Accounts?sortby=started\u0026order=desc\u0026datecut=9999\u0026prefix=0",
    "title": "5 X Hayu",
    "author": "theovan",
    "link": "https://breachforums.jp/Thread-5-X-Hayu",
    "detection-date": "2026-02-05T09:02:37.428Z",
    "timestamp": "2026-02-05T09:02:37.428Z",
    "thread-id": "Thread-5-X-Hayu",
    "link-hash": "46776c3413f9f13af862840a448cf0150e215a2a98f6deb5ddf5db93188d49dd"
  },
  {
    "name": "htdark-combolist",
    "source": "https://htdark.com/forums/proxy-lists-combolists.189/",
    "title": "4.02.26 MIX Unique Combo_6_27000",
    "author": "UniqueCombo",
    "link": "https://htdark.com/threads/4-02-26-mix-unique-combo_6_27000.141059/",
    "detection-date": "2026-02-05T09:02:41.571Z",
    "timestamp": "2026-02-05T09:02:41.571Z",
    "thread-id": "4",
    "link-hash": "b7cd3c574eab00a87210f3feb7e1489d8e4e00d83516bbb332259477e867282e"
  },
  {
    "name": "breachforums-database",
    "source": "https://breachforums.jp/Forum-Databases?sortby=started\u0026order=desc\u0026datecut=9999\u0026prefix=0",
    "title": "EverythingCheerAndDance.com",
    "author": "ldopanda2",
    "link": "https://breachforums.jp/Thread-DATABASE-EverythingCheerAndDance-com",
    "detection-date": "2026-02-05T09:11:58.373Z",
    "timestamp": "2026-02-05T09:11:58.373Z",
    "thread-id": "Thread-DATABASE-EverythingCheerAndDance-com",
    "link-hash": "fa0edad03eafbc9e29acbedb1f023f0387c58c3bcf94914bbb7c5d5627c5b659"
  },
  {
    "name": "crackingx-latest",
    "source": "https://crackingx.com/whats-new/posts/2205517/",
    "title": "325GB URL-LOG-PASS PRIVATE WITH ONLINE ROBOT FOR SEARCH YOUR TARGET",
    "author": "Wise",
    "link": "https://crackingx.com/threads/64498/",
    "detection-date": "2026-02-05T09:12:02.069Z",
    "timestamp": "2026-02-05T09:12:02.069Z",
    "thread-id": "64498",
    "link-hash": "e5e7cb6cf4661c0000c9015e6d3172a3ddb97d901907347cfa8bddf1d1778c26"
  },
  {
    "name": "breachforums-database",
    "source": "https://breachforums.jp/Forum-Databases?sortby=started\u0026order=desc\u0026datecut=9999\u0026prefix=0",
    "title": "US residents. Around 2 billion lines",
    "author": "7pFT54FFdO",
    "link": "https://breachforums.jp/Thread-US-residents-Around-2-billion-lines",
    "detection-date": "2026-02-05T09:16:36.182Z",
    "timestamp": "2026-02-05T09:16:36.182Z",
    "thread-id": "Thread-US-residents-Around-2-billion-lines",
    "link-hash": "830988682e516c9bac46daac7ac362f6c28244ead19da061d7124dd344490aac"
  },
  {
    "name": "darkforums-stealer-logs",
    "source": "https://darkforums.me/Forum-Stealer-Logs?sortby=started\u0026order=desc\u0026datecut=9999\u0026prefix=0",
    "title": "⚡[9.4M] - URL:LOG:PASS || PRIVATE || UHQ⚡",
    "author": "RedCloud",
    "link": "https://darkforums.me/Thread-%E2%9A%A1-9-4M-URL-LOG-PASS-PRIVATE-UHQ%E2%9A%A1",
    "detection-date": "2026-02-05T09:16:41.122Z",
    "timestamp": "2026-02-05T09:16:41.122Z",
    "thread-id": "Thread-%E2%9A%A1-9-4M-URL-LOG-PASS-PRIVATE-UHQ%E2%9A%A1",
    "link-hash": "b1908975b37c1e9439476a3f8b5269efb3482c352807167abb6fa66bdb92823f"
  },
  {
    "name": "darkforums-database",
    "source": "https://darkforums.me/Forum-Databases?sortby=started\u0026order=desc\u0026datecut=9999\u0026prefix=0",
    "title": "Flair Airlines Vulnerabilities + Access and Data Extraction Method",
    "author": "GordonFreeman",
    "link": "https://darkforums.me/Thread-DATABASE-Flair-Airlines-Vulnerabilities-Access-and-Data-Extraction-Method",
    "detection-date": "2026-02-05T09:16:41.432Z",
    "timestamp": "2026-02-05T09:16:41.432Z",
    "thread-id": "Thread-DATABASE-Flair-Airlines-Vulnerabilities-Access-and-Data-Extraction-Method",
    "link-hash": "8cb506e10844ba3d5606cad9b33fd2facaae85cf5a66032a63ea28b9dd7f529d"
  },
  {
    "name": "darkforums-combolists",
    "source": "https://darkforums.me/Forum-Combolists?sortby=started\u0026order=desc\u0026datecut=9999\u0026prefix=0",
    "title": "✦✦ [ 19 K++ ] Combo✦{ Taiwan }✦ Email:Pass ✦FRESH✦ [ 5-2-2026 ] ✦✦",
    "author": "Max_Leaks",
    "link": "https://darkforums.me/Thread-Document-%E2%9C%A6%E2%9C%A6-19-K-Combo%E2%9C%A6-Taiwan-%E2%9C%A6-Email-Pass-%E2%9C%A6FRESH%E2%9C%A6-5-2-2026-%E2%9C%A6%E2%9C%A6",
    "detection-date": "2026-02-05T09:16:43.873Z",
    "timestamp": "2026-02-05T09:16:43.873Z",
    "thread-id": "",
    "link-hash": "19b173d666ab4f24bbe2588b0abee4361c2e9ce87e08aa7d473006f6f976ea14"
  },
  {
    "name": "darkforums-other-leaks",
    "source": "https://darkforums.me/Forum-Other-Leaks?sortby=started\u0026order=desc\u0026datecut=9999\u0026prefix=0",
    "title": "ELC Electroconsult SpA DataBase (90 GB)",
    "author": "ibaibai2022",
    "link": "https://darkforums.me/Thread-ELC-Electroconsult-SpA-DataBase-90-GB",
    "detection-date": "2026-02-05T09:16:44.042Z",
    "timestamp": "2026-02-05T09:16:44.042Z",
    "thread-id": "Thread-ELC-Electroconsult-SpA-DataBase-90-GB",
    "link-hash": "c36016cac251431b7e525cf62af2b356759d884fc2b7fdf97b638a5eaa925182"
  },
  {
    "name": "patched-combolist",
    "source": "https://patched.to/Forum-combolist?sortby=started\u0026order=desc\u0026datecut=9999\u0026prefix=0",
    "title": "SKYLIGHT CLOUD HOTMAIL",
    "author": "SkylightCloud",
    "link": "https://patched.to/Thread-file-upload-skylight-cloud-hotmail-269832",
    "detection-date": "2026-02-05T09:23:20.379Z",
    "timestamp": "2026-02-05T09:23:20.379Z",
    "thread-id": "Thread-file-upload-skylight-cloud-hotmail-269832",
    "link-hash": "35b9b546bda33f692dce2af9d08f71ac5fd0a0a511bf7376c98a25d142119a95"
  },
  {
    "name": "patched-accounts",
    "source": "https://patched.to/Forum-accounts?sortby=started\u0026order=desc\u0026datecut=9999\u0026prefix=0",
    "title": "[✨ 55X PLEXTV HITS UHQ ✨]",
    "author": "batophobia",
    "link": "https://patched.to/Thread-%E2%9C%A8-55x-plextv-hits-uhq-%E2%9C%A8",
    "detection-date": "2026-02-05T09:28:40.209Z",
    "timestamp": "2026-02-05T09:28:40.209Z",
    "thread-id": "Thread-%E2%9C%A8-55x-plextv-hits-uhq-%E2%9C%A8",
    "link-hash": "f67e218feb1e1f301119e4a0766f0e2ed5f63ad34b6e11aa0cd1d73ab4c4c627"
  },
  {
    "name": "breachforums-database",
    "source": "https://breachforums.jp/Forum-Databases?sortby=started\u0026order=desc\u0026datecut=9999\u0026prefix=0",
    "title": "literaturabrasileira.ufsc.br",
    "author": "ldopanda2",
    "link": "https://breachforums.jp/Thread-DATABASE-literaturabrasileira-ufsc-br",
    "detection-date": "2026-02-05T09:49:49.650Z",
    "timestamp": "2026-02-05T09:49:49.650Z",
    "thread-id": "Thread-DATABASE-literaturabrasileira-ufsc-br",
    "link-hash": "cd15f81ed07f28de707366f4566e014c15b72a27d68ddee210438a28aa637871"
  },
  {
    "name": "patched-combolist",
    "source": "https://patched.to/Forum-combolist?sortby=started\u0026order=desc\u0026datecut=9999\u0026prefix=0",
    "title": "SKYLIGHT CLOUD HOTMAIL",
    "author": "SkylightCloud",
    "link": "https://patched.to/Thread-file-upload-skylight-cloud-hotmail-269840",
    "detection-date": "2026-02-05T09:49:57.107Z",
    "timestamp": "2026-02-05T09:49:57.107Z",
    "thread-id": "Thread-file-upload-skylight-cloud-hotmail-269840",
    "link-hash": "50a123190c911a84c6a97ad91fec8c92bbf0f6e2cf02be2b6af9fbbf885f6de8"
  },
  {
    "name": "nulledbb-cracking",
    "source": "https://nulledbb.com/forum-Cracking-Proxies-and-Wordlists",
    "title": "❄️❄️ 3398x PREMIUM HOTMAIL HITS ❄️❄️",
    "author": "Xdalpha",
    "link": "https://nulledbb.com/thread-%E2%9D%84%EF%B8%8F%E2%9D%84%EF%B8%8F-3398x-PREMIUM-HOTMAIL-HITS-%E2%9D%84%EF%B8%8F%E2%9D%84%EF%B8%8F",
    "detection-date": "2026-02-05T09:50:00.571Z",
    "timestamp": "2026-02-05T09:50:00.571Z",
    "thread-id": "",
    "link-hash": "07038909412adf26650bb9b25eb5ce95d9764802b8f8961857f2555846c92567"
  },
  {
    "name": "patched-combolist",
    "source": "https://patched.to/Forum-combolist?sortby=started\u0026order=desc\u0026datecut=9999\u0026prefix=0",
    "title": "Url:Log:Pass 8+ Mıllıon Lınes part: 100",
    "author": "lexityfr",
    "link": "https://patched.to/Thread-file-upload-url-log-pass-8-million-lines-part-100",
    "detection-date": "2026-02-05T09:52:15.044Z",
    "timestamp": "2026-02-05T09:52:15.044Z",
    "thread-id": "Thread-file-upload-url-log-pass-8-million-lines-part-100",
    "link-hash": "751d2a2b234a7eb3ceccf2a7e4cb828319c365aa97589e2b403c34585e728d5f"
  },
  {
    "name": "nulledbb-cracking",
    "source": "https://nulledbb.com/forum-Cracking-Proxies-and-Wordlists?sortby=started\u0026order=desc\u0026datecut=9999\u0026prefix=0",
    "title": "⚡[9.4M] - URL:LOG:PASS || PRIVATE || UHQ⚡",
    "author": "tutuba4m",
    "link": "https://nulledbb.com/thread-%E2%9A%A1-9-4M-URL-LOG-PASS-PRIVATE-UHQ%E2%9A%A1--2282571",
    "detection-date": "2026-02-05T09:52:17.219Z",
    "timestamp": "2026-02-05T09:52:17.219Z",
    "thread-id": "thread-%E2%9A%A1-9-4M-URL-LOG-PASS-PRIVATE-UHQ%E2%9A%A1--2282571",
    "link-hash": "e4e06cb6b5749c2ff5702142eee090f4c5864fb6dc4853c8b92bbfd0fef680cc"
  },
  {
    "name": "nulledbb-configs",
    "source": "https://nulledbb.com/forum-Cracking-Configs?sortby=started\u0026order=desc\u0026datecut=9999\u0026prefix=0",
    "title": "SilverBullet Config X.COM + 40 More - HIGH CPM | February 2026",
    "author": "silverbuldev",
    "link": "https://nulledbb.com/thread-OpenBullet-SilverBullet-Config-X-COM-40-More-HIGH-CPM-February-2026",
    "detection-date": "2026-02-05T09:52:18.052Z",
    "timestamp": "2026-02-05T09:52:18.052Z",
    "thread-id": "thread-OpenBullet-SilverBullet-Config-X-COM-40-More-HIGH-CPM-February-2026",
    "link-hash": "be94c7056a1a6988b4e3cfc251c33e41ca6041d43b6f936a6539075887581820"
  },
  {
    "name": "breachforums-stealer-logs",
    "source": "https://breachforums.jp/Forum-Stealer-Logs?sortby=started\u0026order=desc\u0026datecut=9999\u0026prefix=0",
    "title": "FRESH PRIVATE ULP +8M lines 05/02/2026",
    "author": "async42",
    "link": "https://breachforums.jp/Thread-URL-LOGIN-PASS-FRESH-PRIVATE-ULP-8M-lines-05-02-2026",
    "detection-date": "2026-02-05T10:04:02.658Z",
    "timestamp": "2026-02-05T10:04:02.658Z",
    "thread-id": "Thread-URL-LOGIN-PASS-FRESH-PRIVATE-ULP-8M-lines-05-02-2026",
    "link-hash": "791c7bfc5c94d4df32044e4c05b5265238977272d39c3cb0a70da54e3bdd8443"
  },
  {
    "name": "patched-accounts",
    "source": "https://patched.to/Forum-accounts?sortby=started\u0026order=desc\u0026datecut=9999\u0026prefix=0",
    "title": "🌊||🌊X1151 USA-CA-EU MIX EMAIL ACCESS🌊||🌊",
    "author": "ULTRA",
    "link": "https://patched.to/Thread-file-upload-%F0%9F%8C%8A-%F0%9F%8C%8Ax1151-usa-ca-eu-mix-email-access%F0%9F%8C%8A-%F0%9F%8C%8A",
    "detection-date": "2026-02-05T10:04:10.471Z",
    "timestamp": "2026-02-05T10:04:10.471Z",
    "thread-id": "",
    "link-hash": "a7eec6ce15f73c7ceb70c7d680dde9873f2516286235837426237f7e57d38058"
  },
  {
    "name": "patched-combolist",
    "source": "https://patched.to/Forum-combolist?sortby=started\u0026order=desc\u0026datecut=9999\u0026prefix=0",
    "title": "[ ⚡⚡ 1501x FRESH HOTMAIL ⚡⚡ ]",
    "author": "NuIled07",
    "link": "https://patched.to/Thread-file-upload-%E2%9A%A1%E2%9A%A1-1501x-fresh-hotmail-%E2%9A%A1%E2%9A%A1",
    "detection-date": "2026-02-05T10:04:13.183Z",
    "timestamp": "2026-02-05T10:04:13.183Z",
    "thread-id": "Thread-file-upload-%E2%9A%A1%E2%9A%A1-1501x-fresh-hotmail-%E2%9A%A1%E2%9A%A1",
    "link-hash": "222488ea428c2688214a65d85b278addb8ab00151599725463c5c0f7715c4661"
  },
  {
    "name": "patched-combolist",
    "source": "https://patched.to/Forum-combolist?sortby=started\u0026order=desc\u0026datecut=9999\u0026prefix=0",
    "title": "✅ [UHQ] ⭐✨ 300x FULL VALID MAIL ACCESS [FRESH-NO DUPLICATES-TRUSTED]⭐✨✅",
    "author": "NewHere",
    "link": "https://patched.to/Thread-%E2%9C%85-uhq-%E2%AD%90%E2%9C%A8-300x-full-valid-mail-access-fresh-no-duplicates-trusted-%E2%AD%90%E2%9C%A8%E2%9C%85",
    "detection-date": "2026-02-05T11:18:09.160Z",
    "timestamp": "2026-02-05T11:18:09.160Z",
    "thread-id": "",
    "link-hash": "59eb207e4629c668060d09bbcd497e79389f10534163b7b6994d274fb9683709"
  },
  {
    "name": "htdark-combolist",
    "source": "https://htdark.com/forums/proxy-lists-combolists.189/",
    "title": "10K Germany Mail Access By MegaCloud 04.06",
    "author": "MailAccess",
    "link": "https://htdark.com/threads/10k-germany-mail-access-by-megacloud-04-06.141067/",
    "detection-date": "2026-02-05T11:18:10.101Z",
    "timestamp": "2026-02-05T11:18:10.101Z",
    "thread-id": "10",
    "link-hash": "20632048b4507b8e2859e97e2e5552eb414cd13cc8215cac53bee68fe87ecb1f"
  },
  {
    "name": "patched-accounts",
    "source": "https://patched.to/Forum-accounts?sortby=started\u0026order=desc\u0026datecut=9999\u0026prefix=0",
    "title": "✨⚡️1.2k HOTMAIL MAIL ACCESS⚡️✨",
    "author": "TraxGod",
    "link": "https://patched.to/Thread-file-upload-%E2%9C%A8%E2%9A%A1%EF%B8%8F1-2k-hotmail-mail-access%E2%9A%A1%EF%B8%8F%E2%9C%A8-269854",
    "detection-date": "2026-02-05T11:18:12.681Z",
    "timestamp": "2026-02-05T11:18:12.681Z",
    "thread-id": "",
    "link-hash": "8df7d11e515b4d105216f0caa44304d531235473c52860662f3da1b04de01b86"
  },
  {
    "name": "breachforums-stealer-logs",
    "source": "https://breachforums.jp/Forum-Stealer-Logs?sortby=started\u0026order=desc\u0026datecut=9999\u0026prefix=0",
    "title": "FRESH PRIVATE ULP +8M lines 05/02/2026",
    "author": "async42",
    "link": "https://breachforums.jp/Thread-URL-LOGIN-PASS-FRESH-PRIVATE-ULP-8M-lines-05-02-2026",
    "detection-date": "2026-02-05T11:19:11.008Z",
    "timestamp": "2026-02-05T11:19:11.008Z",
    "thread-id": "Thread-URL-LOGIN-PASS-FRESH-PRIVATE-ULP-8M-lines-05-02-2026",
    "link-hash": "791c7bfc5c94d4df32044e4c05b5265238977272d39c3cb0a70da54e3bdd8443"
  },
  {
    "name": "breachforums-cracked-accounts",
    "source": "https://breachforums.jp/Forum-Cracked-Accounts?sortby=started\u0026order=desc\u0026datecut=9999\u0026prefix=0",
    "title": "5 X Hayu",
    "author": "theovan",
    "link": "https://breachforums.jp/Thread-5-X-Hayu",
    "detection-date": "2026-02-05T11:19:11.026Z",
    "timestamp": "2026-02-05T11:19:11.026Z",
    "thread-id": "Thread-5-X-Hayu",
    "link-hash": "46776c3413f9f13af862840a448cf0150e215a2a98f6deb5ddf5db93188d49dd"
  },
  {
    "name": "crackingx-latest",
    "source": "https://crackingx.com/whats-new/posts/2205517/",
    "title": "325GB URL-LOG-PASS PRIVATE WITH ONLINE ROBOT FOR SEARCH YOUR TARGET",
    "author": "Wise",
    "link": "https://crackingx.com/threads/64498/",
    "detection-date": "2026-02-05T11:19:13.859Z",
    "timestamp": "2026-02-05T11:19:13.859Z",
    "thread-id": "64498",
    "link-hash": "e5e7cb6cf4661c0000c9015e6d3172a3ddb97d901907347cfa8bddf1d1778c26"
  },
  {
    "name": "darkforums-database",
    "source": "https://darkforums.me/Forum-Databases?sortby=started\u0026order=desc\u0026datecut=9999\u0026prefix=0",
    "title": "Flair Airlines Vulnerabilities + Access and Data Extraction Method",
    "author": "GordonFreeman",
    "link": "https://darkforums.me/Thread-DATABASE-Flair-Airlines-Vulnerabilities-Access-and-Data-Extraction-Method",
    "detection-date": "2026-02-05T11:19:13.887Z",
    "timestamp": "2026-02-05T11:19:13.887Z",
    "thread-id": "Thread-DATABASE-Flair-Airlines-Vulnerabilities-Access-and-Data-Extraction-Method",
    "link-hash": "8cb506e10844ba3d5606cad9b33fd2facaae85cf5a66032a63ea28b9dd7f529d"
  },
  {
    "name": "htdark-combolist",
    "source": "https://htdark.com/forums/proxy-lists-combolists.189/",
    "title": "10K Germany Mail Access By MegaCloud 04.06",
    "author": "MailAccess",
    "link": "https://htdark.com/threads/10k-germany-mail-access-by-megacloud-04-06.141067/",
    "detection-date": "2026-02-05T11:19:15.843Z",
    "timestamp": "2026-02-05T11:19:15.843Z",
    "thread-id": "10",
    "link-hash": "20632048b4507b8e2859e97e2e5552eb414cd13cc8215cac53bee68fe87ecb1f"
  },
  {
    "name": "darkforums-stealer-logs",
    "source": "https://darkforums.me/Forum-Stealer-Logs?sortby=started\u0026order=desc\u0026datecut=9999\u0026prefix=0",
    "title": "⚡[9.4M] - URL:LOG:PASS || PRIVATE || UHQ⚡",
    "author": "RedCloud",
    "link": "https://darkforums.me/Thread-%E2%9A%A1-9-4M-URL-LOG-PASS-PRIVATE-UHQ%E2%9A%A1",
    "detection-date": "2026-02-05T11:19:16.670Z",
    "timestamp": "2026-02-05T11:19:16.670Z",
    "thread-id": "Thread-%E2%9A%A1-9-4M-URL-LOG-PASS-PRIVATE-UHQ%E2%9A%A1",
    "link-hash": "b1908975b37c1e9439476a3f8b5269efb3482c352807167abb6fa66bdb92823f"
  },
  {
    "name": "darkforums-combolists",
    "source": "https://darkforums.me/Forum-Combolists?sortby=started\u0026order=desc\u0026datecut=9999\u0026prefix=0",
    "title": "✦✦ [ 19 K++ ] Combo✦{ Taiwan }✦ Email:Pass ✦FRESH✦ [ 5-2-2026 ] ✦✦",
    "author": "Max_Leaks",
    "link": "https://darkforums.me/Thread-Document-%E2%9C%A6%E2%9C%A6-19-K-Combo%E2%9C%A6-Taiwan-%E2%9C%A6-Email-Pass-%E2%9C%A6FRESH%E2%9C%A6-5-2-2026-%E2%9C%A6%E2%9C%A6",
    "detection-date": "2026-02-05T11:19:16.707Z",
    "timestamp": "2026-02-05T11:19:16.707Z",
    "thread-id": "",
    "link-hash": "19b173d666ab4f24bbe2588b0abee4361c2e9ce87e08aa7d473006f6f976ea14"
  },
  {
    "name": "darkforums-other-leaks",
    "source": "https://darkforums.me/Forum-Other-Leaks?sortby=started\u0026order=desc\u0026datecut=9999\u0026prefix=0",
    "title": "ELC Electroconsult SpA DataBase (90 GB)",
    "author": "ibaibai2022",
    "link": "https://darkforums.me/Thread-ELC-Electroconsult-SpA-DataBase-90-GB",
    "detection-date": "2026-02-05T11:19:18.594Z",
    "timestamp": "2026-02-05T11:19:18.594Z",
    "thread-id": "Thread-ELC-Electroconsult-SpA-DataBase-90-GB",
    "link-hash": "c36016cac251431b7e525cf62af2b356759d884fc2b7fdf97b638a5eaa925182"
  },
  {
    "name": "patched-combolist",
    "source": "https://patched.to/Forum-combolist?sortby=started\u0026order=desc\u0026datecut=9999\u0026prefix=0",
    "title": "✅ [UHQ] ⭐✨ 300x FULL VALID MAIL ACCESS [FRESH-NO DUPLICATES-TRUSTED]⭐✨✅",
    "author": "NewHere",
    "link": "https://patched.to/Thread-%E2%9C%85-uhq-%E2%AD%90%E2%9C%A8-300x-full-valid-mail-access-fresh-no-duplicates-trusted-%E2%AD%90%E2%9C%A8%E2%9C%85",
    "detection-date": "2026-02-05T11:19:19.272Z",
    "timestamp": "2026-02-05T11:19:19.272Z",
    "thread-id": "",
    "link-hash": "59eb207e4629c668060d09bbcd497e79389f10534163b7b6994d274fb9683709"
  },
  {
    "name": "patched-accounts",
    "source": "https://patched.to/Forum-accounts?sortby=started\u0026order=desc\u0026datecut=9999\u0026prefix=0",
    "title": "✨⚡️1.2k HOTMAIL MAIL ACCESS⚡️✨",
    "author": "TraxGod",
    "link": "https://patched.to/Thread-file-upload-%E2%9C%A8%E2%9A%A1%EF%B8%8F1-2k-hotmail-mail-access%E2%9A%A1%EF%B8%8F%E2%9C%A8-269854",
    "detection-date": "2026-02-05T11:19:19.343Z",
    "timestamp": "2026-02-05T11:19:19.343Z",
    "thread-id": "",
    "link-hash": "8df7d11e515b4d105216f0caa44304d531235473c52860662f3da1b04de01b86"
  },
  {
    "name": "nulledbb-cracking",
    "source": "https://nulledbb.com/forum-Cracking-Proxies-and-Wordlists?sortby=started\u0026order=desc\u0026datecut=9999\u0026prefix=0",
    "title": "⚡[9.4M] - URL:LOG:PASS || PRIVATE || UHQ⚡",
    "author": "tutuba4m",
    "link": "https://nulledbb.com/thread-%E2%9A%A1-9-4M-URL-LOG-PASS-PRIVATE-UHQ%E2%9A%A1--2282571",
    "detection-date": "2026-02-05T11:19:21.202Z",
    "timestamp": "2026-02-05T11:19:21.202Z",
    "thread-id": "thread-%E2%9A%A1-9-4M-URL-LOG-PASS-PRIVATE-UHQ%E2%9A%A1--2282571",
    "link-hash": "e4e06cb6b5749c2ff5702142eee090f4c5864fb6dc4853c8b92bbfd0fef680cc"
  },
  {
    "name": "nulledbb-configs",
    "source": "https://nulledbb.com/forum-Cracking-Configs?sortby=started\u0026order=desc\u0026datecut=9999\u0026prefix=0",
    "title": "SilverBullet Config X.COM + 40 More - HIGH CPM | February 2026",
    "author": "silverbuldev",
    "link": "https://nulledbb.com/thread-OpenBullet-SilverBullet-Config-X-COM-40-More-HIGH-CPM-February-2026",
    "detection-date": "2026-02-05T11:19:21.883Z",
    "timestamp": "2026-02-05T11:19:21.883Z",
    "thread-id": "thread-OpenBullet-SilverBullet-Config-X-COM-40-More-HIGH-CPM-February-2026",
    "link-hash": "be94c7056a1a6988b4e3cfc251c33e41ca6041d43b6f936a6539075887581820"
  },
  {
    "name": "breachforums-database",
    "source": "https://breachforums.jp/Forum-Databases?sortby=started\u0026order=desc\u0026datecut=9999\u0026prefix=0",
    "title": "literaturabrasileira.ufsc.br",
    "author": "ldopanda2",
    "link": "https://breachforums.jp/Thread-DATABASE-literaturabrasileira-ufsc-br",
    "detection-date": "2026-02-05T11:19:22.000Z",
    "timestamp": "2026-02-05T11:19:22.000Z",
    "thread-id": "Thread-DATABASE-literaturabrasileira-ufsc-br",
    "link-hash": "cd15f81ed07f28de707366f4566e014c15b72a27d68ddee210438a28aa637871"
  },
  {
    "name": "breachforums-combolists",
    "source": "https://breachforums.jp/Forum-Combolists?sortby=started\u0026order=desc\u0026datecut=9999\u0026prefix=0",
    "title": "❄️❄️ 3398x PREMIUM HOTMAIL HITS ❄️❄️",
    "author": "xdalpha",
    "link": "https://breachforums.jp/Thread-%E2%9D%84%EF%B8%8F%E2%9D%84%EF%B8%8F-3398x-PREMIUM-HOTMAIL-HITS-%E2%9D%84%EF%B8%8F%E2%9D%84%EF%B8%8F",
    "detection-date": "2026-02-05T11:19:23.832Z",
    "timestamp": "2026-02-05T11:19:23.832Z",
    "thread-id": "",
    "link-hash": "8c081716f634b045e437fd26a72fcd835fcc378a5adc030c2c5e891aaae01dc8"
  },
  {
    "name": "htdark-combolist",
    "source": "https://htdark.com/forums/proxy-lists-combolists.189/",
    "title": "4.6K ✈️HOTMAIL✈️ Fresh ✈️ Just Valid Mail ✈️By MegaCloud 05.02",
    "author": "MailAccess",
    "link": "https://htdark.com/threads/4-6k-hotmail-fresh-just-valid-mail-by-megacloud-05-02.141069/",
    "detection-date": "2026-02-05T11:39:42.405Z",
    "timestamp": "2026-02-05T11:39:42.405Z",
    "thread-id": "4",
    "link-hash": "5a4f7bef938cd50881c5014613908e1cd78b38e06dd2349fdf48c9fe8d68f813"
  },
  {
    "name": "patched-combolist",
    "source": "https://patched.to/Forum-combolist?sortby=started\u0026order=desc\u0026datecut=9999\u0026prefix=0",
    "title": "⚡3k JAPAN MAIL ACCESS⚡",
    "author": "WashingtonDC",
    "link": "https://patched.to/Thread-%E2%9A%A13k-japan-mail-access%E2%9A%A1",
    "detection-date": "2026-02-05T11:39:45.099Z",
    "timestamp": "2026-02-05T11:39:45.099Z",
    "thread-id": "Thread-%E2%9A%A13k-japan-mail-access%E2%9A%A1",
    "link-hash": "6b97f003dcb2723a551e7e40761ed484119c736e28498479ab5e3bbed02228d2"
  },
  {
    "name": "nulledbb-cracking",
    "source": "https://nulledbb.com/forum-Cracking-Proxies-and-Wordlists?sortby=started\u0026order=desc\u0026datecut=9999\u0026prefix=0",
    "title": "❄️❄️ 3398x PREMIUM HOTMAIL HITS ❄️❄️",
    "author": "Xdalpha",
    "link": "https://nulledbb.com/thread-%E2%9D%84%EF%B8%8F%E2%9D%84%EF%B8%8F-3398x-PREMIUM-HOTMAIL-HITS-%E2%9D%84%EF%B8%8F%E2%9D%84%EF%B8%8F",
    "detection-date": "2026-02-05T11:39:46.247Z",
    "timestamp": "2026-02-05T11:39:46.247Z",
    "thread-id": "",
    "link-hash": "07038909412adf26650bb9b25eb5ce95d9764802b8f8961857f2555846c92567"
  },
  {
    "name": "leakforum-other-leaks",
    "source": "https://leakforum.io/Forum-Other-Leaks?sortby=started\u0026order=desc\u0026datecut=9999\u0026prefix=0",
    "title": "Telegram Groups: Regional Marketplaces | 300+ Country Groups",
    "author": "Karma",
    "link": "https://leakforum.io/Thread-Telegram-Groups-Regional-Marketplaces-300-Country-Groups",
    "detection-date": "2026-02-05T11:39:47.840Z",
    "timestamp": "2026-02-05T11:39:47.840Z",
    "thread-id": "Thread-Telegram-Groups-Regional-Marketplaces-300-Country-Groups",
    "link-hash": "2ed49788922c6cebd4dd8bcb9f7d10fce96394a5b269c326a1c10419e9f79d0c"
  },
  {
    "name": "leakforum-other-leaks",
    "source": "https://leakforum.io/Forum-Other-Leaks?sortby=started\u0026order=desc\u0026datecut=9999\u0026prefix=0",
    "title": "Telegram Groups: Regional Marketplaces | 300+ Country Groups",
    "author": "Karma",
    "link": "https://leakforum.io/Thread-Telegram-Groups-Regional-Marketplaces-300-Country-Groups",
    "detection-date": "2026-02-05T11:41:56.570Z",
    "timestamp": "2026-02-05T11:41:56.570Z",
    "thread-id": "Thread-Telegram-Groups-Regional-Marketplaces-300-Country-Groups",
    "link-hash": "2ed49788922c6cebd4dd8bcb9f7d10fce96394a5b269c326a1c10419e9f79d0c"
  },
  {
    "name": "patched-combolist",
    "source": "https://patched.to/Forum-combolist?sortby=started\u0026order=desc\u0026datecut=9999\u0026prefix=0",
    "title": "✅ [UHQ] ⭐✨ 380x FULL VALID MAIL ACCESS [FRESH-NO DUPLICATES-TRUSTED]⭐✨✅",
    "author": "NewHere",
    "link": "https://patched.to/Thread-file-upload-%E2%9C%85-uhq-%E2%AD%90%E2%9C%A8-380x-full-valid-mail-access-fresh-no-duplicates-trusted-%E2%AD%90%E2%9C%A8%E2%9C%85",
    "detection-date": "2026-02-05T12:05:03.381Z",
    "timestamp": "2026-02-05T12:05:03.381Z",
    "thread-id": "",
    "link-hash": "3baf44bd1ea191676a24da5cf9a9d09cba35af62f0f84c9ab0ccebfec8b19c97"
  },
  {
    "name": "breachforums-database",
    "source": "https://breachforums.jp/Forum-Databases?sortby=started\u0026order=desc\u0026datecut=9999\u0026prefix=0",
    "title": "EcoATM 2013",
    "author": "zvezdanwastaken",
    "link": "https://breachforums.jp/Thread-DATABASE-EcoATM-2013",
    "detection-date": "2026-02-05T12:05:08.968Z",
    "timestamp": "2026-02-05T12:05:08.968Z",
    "thread-id": "Thread-DATABASE-EcoATM-2013",
    "link-hash": "c53ec3d68b73d361246526f7296272dd3c71bea9580cd3926e38ac235be6e4cd"
  },
  {
    "name": "darkforums-combolists",
    "source": "https://darkforums.me/Forum-Combolists?sortby=started\u0026order=desc\u0026datecut=9999\u0026prefix=0",
    "title": "4.6K ✈️HOTMAIL✈️ Fresh ✈️ Just Valid Mail ✈️By MegaCloud 05.02",
    "author": "MegaCloud",
    "link": "https://darkforums.me/Thread-4-6K-%E2%9C%88%EF%B8%8FHOTMAIL%E2%9C%88%EF%B8%8F-Fresh-%E2%9C%88%EF%B8%8F-Just-Valid-Mail-%E2%9C%88%EF%B8%8FBy-MegaCloud-05-02",
    "detection-date": "2026-02-05T12:07:00.148Z",
    "timestamp": "2026-02-05T12:07:00.148Z",
    "thread-id": "",
    "link-hash": "8a9adaacb41cc2ffd3898a63dffc0bcf12e3b8d263f5c8bced6576c02f3b661a"
  },
  {
    "name": "breachforums-database",
    "source": "https://breachforums.jp/Forum-Databases?sortby=started\u0026order=desc\u0026datecut=9999\u0026prefix=0",
    "title": "class.am",
    "author": "c0mmandor",
    "link": "https://breachforums.jp/Thread-COLLECTION-class-am",
    "detection-date": "2026-02-05T12:07:06.699Z",
    "timestamp": "2026-02-05T12:07:06.699Z",
    "thread-id": "Thread-COLLECTION-class-am",
    "link-hash": "a318145922dd3015bc75d237050e71515406d2b2a1079be2f3d5ac473cb5fc5f"
  },
  {
    "name": "nulledbb-cracking",
    "source": "https://nulledbb.com/forum-Cracking-Proxies-and-Wordlists?sortby=started\u0026order=desc\u0026datecut=9999\u0026prefix=0",
    "title": "4.6K ✈️HOTMAIL✈️ Fresh ✈️ Just Valid Mail ✈️By MegaCloud 05.02",
    "author": "MegaCloud",
    "link": "https://nulledbb.com/thread-4-6K-%E2%9C%88%EF%B8%8FHOTMAIL%E2%9C%88%EF%B8%8F-Fresh-%E2%9C%88%EF%B8%8F-Just-Valid-Mail-%E2%9C%88%EF%B8%8FBy-MegaCloud-05-02",
    "detection-date": "2026-02-05T12:08:03.621Z",
    "timestamp": "2026-02-05T12:08:03.621Z",
    "thread-id": "4",
    "link-hash": "ff5292d279ee519aee911247968041b29b648c0af624c5785903c58399318461"
  },
  {
    "name": "htdark-combolist",
    "source": "https://htdark.com/forums/proxy-lists-combolists.189/",
    "title": "49K Germany Fresh Mail Access Just Valid Mail By MegaCloud 05.02",
    "author": "MailAccess",
    "link": "https://htdark.com/threads/49k-germany-fresh-mail-access-just-valid-mail-by-megacloud-05-02.141070/",
    "detection-date": "2026-02-05T12:09:05.685Z",
    "timestamp": "2026-02-05T12:09:05.685Z",
    "thread-id": "49",
    "link-hash": "86880157c6480e6e386a56fd3f5b965b95cab409ae2ed3297b5f30680370a0c9"
  },
  {
    "name": "patched-combolist",
    "source": "https://patched.to/Forum-combolist?sortby=started\u0026order=desc\u0026datecut=9999\u0026prefix=0",
    "title": "49K Germany Fresh Mail Access Just Valid Mail 05.02",
    "author": "MailMarket",
    "link": "https://patched.to/Thread-file-upload-49k-germany-fresh-mail-access-just-valid-mail-05-02",
    "detection-date": "2026-02-05T12:10:06.278Z",
    "timestamp": "2026-02-05T12:10:06.278Z",
    "thread-id": "Thread-file-upload-49k-germany-fresh-mail-access-just-valid-mail-05-02",
    "link-hash": "5027af457429563d7e43dcf3c9d4352da49eb147ac0d425bc59f696381bea9cd"
  },
  {
    "name": "patched-combolist",
    "source": "https://patched.to/Forum-combolist?sortby=started\u0026order=desc\u0026datecut=9999\u0026prefix=0",
    "title": "25K CORP \u0026 Mix Full Valid Mail Access 05.02",
    "author": "MailMarket",
    "link": "https://patched.to/Thread-file-upload-25k-corp-mix-full-valid-mail-access-05-02",
    "detection-date": "2026-02-05T12:16:05.235Z",
    "timestamp": "2026-02-05T12:16:05.235Z",
    "thread-id": "Thread-file-upload-25k-corp-mix-full-valid-mail-access-05-02",
    "link-hash": "d313150cfec1fa206e3c484c3882b347f619ac5caf46748ee8086dad3b0493b9"
  },
  {
    "name": "htdark-combolist",
    "source": "https://htdark.com/forums/proxy-lists-combolists.189/",
    "title": "25K CORP \u0026 Mix Full Valid Mail Access By MegaCloud 05.02",
    "author": "MailAccess",
    "link": "https://htdark.com/threads/25k-corp-mix-full-valid-mail-access-by-megacloud-05-02.141071/",
    "detection-date": "2026-02-05T12:17:04.929Z",
    "timestamp": "2026-02-05T12:17:04.929Z",
    "thread-id": "25",
    "link-hash": "248744ca7aff6296bb1cba02d3bdeaae78753a5ba831d5aa41772915d8609008"
  },
  {
    "name": "nulledbb-cracking",
    "source": "https://nulledbb.com/forum-Cracking-Proxies-and-Wordlists?sortby=started\u0026order=desc\u0026datecut=9999\u0026prefix=0",
    "title": "49K Germany Fresh Mail Access Just Valid Mail By MegaCloud 05.02",
    "author": "MegaCloud",
    "link": "https://nulledbb.com/thread-49K-Germany-Fresh-Mail-Access-Just-Valid-Mail-By-MegaCloud-05-02",
    "detection-date": "2026-02-05T12:18:11.452Z",
    "timestamp": "2026-02-05T12:18:11.452Z",
    "thread-id": "49",
    "link-hash": "75c4fa232f430f151a4b35efe31fce8bd3048ad25d7c7dc53d517c7ed82390bd"
  },
  {
    "name": "htdark-combolist",
    "source": "https://htdark.com/forums/proxy-lists-combolists.189/",
    "title": "5.02.26 Hotmail Unique Combo_2_20000",
    "author": "UniqueCombo",
    "link": "https://htdark.com/threads/5-02-26-hotmail-unique-combo_2_20000.141072/",
    "detection-date": "2026-02-05T12:59:03.470Z",
    "timestamp": "2026-02-05T12:59:03.470Z",
    "thread-id": "5",
    "link-hash": "e108c6a908eff05c360b2b998cc5818528fbf208e6a7b9a669c46999f51409e7"
  },
  {
    "name": "patched-combolist",
    "source": "https://patched.to/Forum-combolist?sortby=started\u0026order=desc\u0026datecut=9999\u0026prefix=0",
    "title": "5.02.26 Hotmail Unique Combo_2_20000",
    "author": "UniqueCombo",
    "link": "https://patched.to/Thread-5-02-26-hotmail-unique-combo-2-20000",
    "detection-date": "2026-02-05T12:59:06.361Z",
    "timestamp": "2026-02-05T12:59:06.361Z",
    "thread-id": "Thread-5-02-26-hotmail-unique-combo-2-20000",
    "link-hash": "502215cea39d8006dad87e86972db20f91c9b321ca9886c293c886ba3ae04847"
  },
  {
    "name": "patched-combolist",
    "source": "https://patched.to/Forum-combolist?sortby=started\u0026order=desc\u0026datecut=9999\u0026prefix=0",
    "title": "⭐️ [ 4600 HOTMAIL ] FRESH UQH | GOODTIME CLOUD⭐️",
    "author": "kaiokhanh",
    "link": "https://patched.to/Thread-file-upload-%E2%AD%90%EF%B8%8F-4600-hotmail-fresh-uqh-goodtime-cloud%E2%AD%90%EF%B8%8F",
    "detection-date": "2026-02-05T13:00:05.871Z",
    "timestamp": "2026-02-05T13:00:05.871Z",
    "thread-id": "Thread-file-upload-%E2%AD%90%EF%B8%8F-4600-hotmail-fresh-uqh-goodtime-cloud%E2%AD%90%EF%B8%8F",
    "link-hash": "cbe0512933604cdffa171cb2a3397b319ef4fe63aae2dc4e2755b8ea84610820"
  },
  {
    "name": "breachforums-database",
    "source": "https://breachforums.jp/Forum-Databases?sortby=started\u0026order=desc\u0026datecut=9999\u0026prefix=0",
    "title": "DATA SISWA SMPN 2 CEPER",
    "author": "ShadowNex",
    "link": "https://breachforums.jp/Thread-DATA-SISWA-SMPN-2-CEPER",
    "detection-date": "2026-02-05T13:01:55.592Z",
    "timestamp": "2026-02-05T13:01:55.592Z",
    "thread-id": "Thread-DATA-SISWA-SMPN-2-CEPER",
    "link-hash": "c4697a61683c2afdd1d9ef5d2f7beba0fbaf10c07b2220fa80a4692e71890e02"
  },
  {
    "name": "patched-combolist",
    "source": "https://patched.to/Forum-combolist?sortby=started\u0026order=desc\u0026datecut=9999\u0026prefix=0",
    "title": "1390x⚡⚡HOTMAIL ACCESS⚡⚡",
    "author": "RedHat29",
    "link": "https://patched.to/Thread-file-upload-1390x%E2%9A%A1%E2%9A%A1hotmail-access%E2%9A%A1%E2%9A%A1",
    "detection-date": "2026-02-05T13:02:05.518Z",
    "timestamp": "2026-02-05T13:02:05.518Z",
    "thread-id": "Thread-file-upload-1390x%E2%9A%A1%E2%9A%A1hotmail-access%E2%9A%A1%E2%9A%A1",
    "link-hash": "b560abcd7022805a69eed1bda33c2e3957d5dd252d2ecd4e148980b7d6c2ef0e"
  },
  {
    "name": "patched-combolist",
    "source": "https://patched.to/Forum-combolist?sortby=started\u0026order=desc\u0026datecut=9999\u0026prefix=0",
    "title": "Free Premium Italy Email List – Batch 4/100",
    "author": "emaildbpro",
    "link": "https://patched.to/Thread-file-upload-free-premium-italy-email-list-%E2%80%93-batch-4-100",
    "detection-date": "2026-02-05T13:04:02.011Z",
    "timestamp": "2026-02-05T13:04:02.011Z",
    "thread-id": "Thread-file-upload-free-premium-italy-email-list-%E2%80%93-batch-4-100",
    "link-hash": "e8ede5f70bfcf27eef750edce49663ab1b914b0bf8476ee9879b3bbf3766bc19"
  },
  {
    "name": "patched-combolist",
    "source": "https://patched.to/Forum-combolist?sortby=started\u0026order=desc\u0026datecut=9999\u0026prefix=0",
    "title": "5k Mixed Full Mailaccess | Resspy Cloud",
    "author": "Resspy",
    "link": "https://patched.to/Thread-file-upload-5k-mixed-full-mailaccess-resspy-cloud-269898",
    "detection-date": "2026-02-05T13:05:00.681Z",
    "timestamp": "2026-02-05T13:05:00.681Z",
    "thread-id": "Thread-file-upload-5k-mixed-full-mailaccess-resspy-cloud-269898",
    "link-hash": "c1b436f24c6b480e673c1e3142cc923c4996622af22918a3f6e94021c0dee72f"
  },
  {
    "name": "patched-combolist",
    "source": "https://patched.to/Forum-combolist?sortby=started\u0026order=desc\u0026datecut=9999\u0026prefix=0",
    "title": "✨ 700x Fresh Hotmail Valid ✨",
    "author": "SNSS",
    "link": "https://patched.to/Thread-contributor-%E2%9C%A8-700x-fresh-hotmail-valid-%E2%9C%A8-269899",
    "detection-date": "2026-02-05T13:07:05.667Z",
    "timestamp": "2026-02-05T13:07:05.667Z",
    "thread-id": "Thread-contributor-%E2%9C%A8-700x-fresh-hotmail-valid-%E2%9C%A8-269899",
    "link-hash": "bc516606242b2ff005d68a682c97cad0426a719a0764ea17812bd95609d10f87"
  },
  {
    "name": "breachforums-combolists",
    "source": "https://breachforums.jp/Forum-Combolists?sortby=started\u0026order=desc\u0026datecut=9999\u0026prefix=0",
    "title": "UHQ MIX 124K",
    "author": "mr_kant",
    "link": "https://breachforums.jp/Thread-UHQ-MIX-124K--186944",
    "detection-date": "2026-02-05T13:11:00.626Z",
    "timestamp": "2026-02-05T13:11:00.626Z",
    "thread-id": "Thread-UHQ-MIX-124K--186944",
    "link-hash": "ab45c6aae197e1729a1036270f52ba96cc3e3a5634123cf0e671147eaf4bb78a"
  },
  {
    "name": "breachforums-database",
    "source": "https://breachforums.jp/Forum-Databases?sortby=started\u0026order=desc\u0026datecut=9999\u0026prefix=0",
    "title": "6.8M Citizens of Argentina with National IDs and e-mails",
    "author": "herefortheoofs",
    "link": "https://breachforums.jp/Thread-DATABASE-6-8M-Citizens-of-Argentina-with-National-IDs-and-e-mails",
    "detection-date": "2026-02-05T13:16:55.546Z",
    "timestamp": "2026-02-05T13:16:55.546Z",
    "thread-id": "Thread-DATABASE-6-8M-Citizens-of-Argentina-with-National-IDs-and-e-mails",
    "link-hash": "adeabc28e6a36c3e7fb1ca7a84bc9d270ded01dbccc06be83fc44dba7857b41f"
  },
  {
    "name": "darkforums-combolists",
    "source": "https://darkforums.me/Forum-Combolists?sortby=started\u0026order=desc\u0026datecut=9999\u0026prefix=0",
    "title": "25K CORP \u0026 Mix Full Valid Mail Access By MegaCloud 05.02",
    "author": "MegaCloud",
    "link": "https://darkforums.me/Thread-25K-CORP-Mix-Full-Valid-Mail-Access-By-MegaCloud-05-02",
    "detection-date": "2026-02-05T13:19:03.151Z",
    "timestamp": "2026-02-05T13:19:03.151Z",
    "thread-id": "Thread-25K-CORP-Mix-Full-Valid-Mail-Access-By-MegaCloud-05-02",
    "link-hash": "452f2a190e77f2b32b9270fd73396ac64a609a7beafc1ab425716a22e5e02428"
  },
  {
    "name": "patched-combolist",
    "source": "https://patched.to/Forum-combolist?sortby=started\u0026order=desc\u0026datecut=9999\u0026prefix=0",
    "title": "✅ HQ HOTMAIL HIT ✅",
    "author": "RetroCloud",
    "link": "https://patched.to/Thread-file-upload-%E2%9C%85-hq-hotmail-hit-%E2%9C%85-269902",
    "detection-date": "2026-02-05T13:23:00.628Z",
    "timestamp": "2026-02-05T13:23:00.628Z",
    "thread-id": "Thread-file-upload-%E2%9C%85-hq-hotmail-hit-%E2%9C%85-269902",
    "link-hash": "21936b64fb911864ea910f16ecb3945491424726645a46ffbb30a5433a962f8d"
  },
  {
    "name": "patched-combolist",
    "source": "https://patched.to/Forum-combolist?sortby=started\u0026order=desc\u0026datecut=9999\u0026prefix=0",
    "title": "6.7K Usa Eu Asia Ru Mail Access Mix 05.02",
    "author": "MailMarket",
    "link": "https://patched.to/Thread-file-upload-6-7k-usa-eu-asia-ru-mail-access-mix-05-02",
    "detection-date": "2026-02-05T13:29:05.729Z",
    "timestamp": "2026-02-05T13:29:05.729Z",
    "thread-id": "Thread-file-upload-6-7k-usa-eu-asia-ru-mail-access-mix-05-02",
    "link-hash": "babfc5b384d7a3ca21a8fc161ff74c1a370411d9ef43e34877dd40eda7ab7a85"
  },
  {
    "name": "htdark-combolist",
    "source": "https://htdark.com/forums/proxy-lists-combolists.189/",
    "title": "6.7K Usa Eu Asia Ru Mail Access Mix by MegaCloud 05.02",
    "author": "MailAccess",
    "link": "https://htdark.com/threads/6-7k-usa-eu-asia-ru-mail-access-mix-by-megacloud-05-02.141075/",
    "detection-date": "2026-02-05T13:30:10.885Z",
    "timestamp": "2026-02-05T13:30:10.885Z",
    "thread-id": "6",
    "link-hash": "37c673e0074f40d9c6cfdcf294a966ff5bbf3f791c68fdd81edcfd9f0ae6dc70"
  },
  {
    "name": "nulledbb-cracking",
    "source": "https://nulledbb.com/forum-Cracking-Proxies-and-Wordlists?sortby=started\u0026order=desc\u0026datecut=9999\u0026prefix=0",
    "title": "25K CORP \u0026 Mix Full Valid Mail Access By MegaCloud 05.02",
    "author": "MegaCloud",
    "link": "https://nulledbb.com/thread-25K-CORP-Mix-Full-Valid-Mail-Access-By-MegaCloud-05-02",
    "detection-date": "2026-02-05T13:31:01.062Z",
    "timestamp": "2026-02-05T13:31:01.062Z",
    "thread-id": "25",
    "link-hash": "31c82579681b3c9a4fd263e084579f83880b05dc38b26b34d04d63f58c555d74"
  },
  {
    "name": "patched-combolist",
    "source": "https://patched.to/Forum-combolist?sortby=started\u0026order=desc\u0026datecut=9999\u0026prefix=0",
    "title": "✨ 340x Fresh Hotmail Valid ✨",
    "author": "SNSS",
    "link": "https://patched.to/Thread-contributor-%E2%9C%A8-340x-fresh-hotmail-valid-%E2%9C%A8",
    "detection-date": "2026-02-05T13:34:03.106Z",
    "timestamp": "2026-02-05T13:34:03.106Z",
    "thread-id": "Thread-contributor-%E2%9C%A8-340x-fresh-hotmail-valid-%E2%9C%A8",
    "link-hash": "74c3befc2d42a1715c668117616d725f5a57d7f1cff0a349016852df24c0bd1a"
  },
  {
    "name": "patched-combolist",
    "source": "https://patched.to/Forum-combolist?sortby=started\u0026order=desc\u0026datecut=9999\u0026prefix=0",
    "title": "[10.700x] Hotmail Access Combo {USA ,Europe ,Asia ,Russian}",
    "author": "Larry_Uchiha",
    "link": "https://patched.to/Thread-file-upload-10-700x-hotmail-access-combo-usa-europe-asia-russian",
    "detection-date": "2026-02-05T13:37:00.566Z",
    "timestamp": "2026-02-05T13:37:00.566Z",
    "thread-id": "Thread-file-upload-10-700x-hotmail-access-combo-usa-europe-asia-russian",
    "link-hash": "56e507679dd78fa3a2df88b0b652cf4606be5c2d958a9308a7cd43f24d4f87a6"
  },
  {
    "name": "patched-combolist",
    "source": "https://patched.to/Forum-combolist?sortby=started\u0026order=desc\u0026datecut=9999\u0026prefix=0",
    "title": "Mix Mail Combo [Hotmail,Outlook,Aol,Gmx,Inbox,Icloud,Live....] 2026-2-3",
    "author": "Larry_Uchiha",
    "link": "https://patched.to/Thread-file-upload-mix-mail-combo-hotmail-outlook-aol-gmx-inbox-icloud-live-2026-2-3",
    "detection-date": "2026-02-05T13:38:06.155Z",
    "timestamp": "2026-02-05T13:38:06.155Z",
    "thread-id": "Thread-file-upload-mix-mail-combo-hotmail-outlook-aol-gmx-inbox-icloud-live-2026-2-3",
    "link-hash": "6386bc63516141d0166e917fac507dc82f5636e3e3cc34dda1b42dc87128d661"
  },
  {
    "name": "patched-combolist",
    "source": "https://patched.to/Forum-combolist?sortby=started\u0026order=desc\u0026datecut=9999\u0026prefix=0",
    "title": "Mix Account Combo [Netflix,OnlyFans,ChatGpt,Xbox,Sony,Discord,FaceBook....] 2026-2-3",
    "author": "Larry_Uchiha",
    "link": "https://patched.to/Thread-file-upload-mix-account-combo-netflix-onlyfans-chatgpt-xbox-sony-discord-facebook-2026-2-3",
    "detection-date": "2026-02-05T13:39:02.885Z",
    "timestamp": "2026-02-05T13:39:02.885Z",
    "thread-id": "Thread-file-upload-mix-account-combo-netflix-onlyfans-chatgpt-xbox-sony-discord-facebook-2026-2-3",
    "link-hash": "030151cb262c964068f3b4c02a7c5531948213d1bf43c92813749c52b3610a19"
  },
  {
    "name": "patched-combolist",
    "source": "https://patched.to/Forum-combolist?sortby=started\u0026order=desc\u0026datecut=9999\u0026prefix=0",
    "title": "[ ⚡⚡ 1763x FRESH HOTMAIL ⚡⚡ ]",
    "author": "NuIled07",
    "link": "https://patched.to/Thread-file-upload-%E2%9A%A1%E2%9A%A1-1763x-fresh-hotmail-%E2%9A%A1%E2%9A%A1",
    "detection-date": "2026-02-05T13:41:04.017Z",
    "timestamp": "2026-02-05T13:41:04.017Z",
    "thread-id": "Thread-file-upload-%E2%9A%A1%E2%9A%A1-1763x-fresh-hotmail-%E2%9A%A1%E2%9A%A1",
    "link-hash": "7c24e28bbe388b8ecdbbe8992d72795d87a43d212e7a042985fe7d2897ca5ad2"
  },
  {
    "name": "patched-combolist",
    "source": "https://patched.to/Forum-combolist?sortby=started\u0026order=desc\u0026datecut=9999\u0026prefix=0",
    "title": "7366 MIX COUNTRY MAIL ACCESS",
    "author": "RandomUpload",
    "link": "https://patched.to/Thread-file-upload-7366-mix-country-mail-access",
    "detection-date": "2026-02-05T13:43:02.343Z",
    "timestamp": "2026-02-05T13:43:02.343Z",
    "thread-id": "Thread-file-upload-7366-mix-country-mail-access",
    "link-hash": "a93030997e6ac0dc0262d1a7b2d6d2356187543743bf4cfd9ba267e541ec2f8e"
  },
  {
    "name": "darkforums-combolists",
    "source": "https://darkforums.me/Forum-Combolists?sortby=started\u0026order=desc\u0026datecut=9999\u0026prefix=0",
    "title": "4.7K Fresh Mail Access Mix By MegaCloud 05.02",
    "author": "MegaCloud",
    "link": "https://darkforums.me/Thread-4-7K-Fresh-Mail-Access-Mix-By-MegaCloud-05-02",
    "detection-date": "2026-02-05T21:47:13.185Z",
    "timestamp": "2026-02-05T21:47:13.185Z",
    "thread-id": "Thread-4-7K-Fresh-Mail-Access-Mix-By-MegaCloud-05-02",
    "link-hash": "06123cccee9dea9bcae3a7746a72e562ebaede0547e85cec2cb0040e8ac141fd"
  },
  {
    "name": "breachforums-database",
    "source": "https://breachforums.jp/Forum-Databases?sortby=started\u0026order=desc\u0026datecut=9999\u0026prefix=0",
    "title": "[FR]EMMAUS",
    "author": "HuntSec",
    "link": "https://breachforums.jp/Thread-DATABASE-FR-EMMAUS",
    "detection-date": "2026-02-05T21:47:13.224Z",
    "timestamp": "2026-02-05T21:47:13.224Z",
    "thread-id": "Thread-DATABASE-FR-EMMAUS",
    "link-hash": "f9abc27c238b90831b7c5bec498504010742d886824abd80e023272875faecf9"
  },
  {
    "name": "breachforums-stealer-logs",
    "source": "https://breachforums.jp/Forum-Stealer-Logs?sortby=started\u0026order=desc\u0026datecut=9999\u0026prefix=0",
    "title": "KeyCat Stealer - Logs",
    "author": "TheKeyCat",
    "link": "https://breachforums.jp/Thread-KeyCat-Stealer-Logs",
    "detection-date": "2026-02-05T21:47:13.241Z",
    "timestamp": "2026-02-05T21:47:13.241Z",
    "thread-id": "Thread-KeyCat-Stealer-Logs",
    "link-hash": "2e829995a8356a4c622eb6ddeadeb08dd13ca755c7ffa5cbdecf35f20d9bacf3"
  },
  {
    "name": "breachforums-combolists",
    "source": "https://breachforums.jp/Forum-Combolists?sortby=started\u0026order=desc\u0026datecut=9999\u0026prefix=0",
    "title": "120K Bulgaria HQ Good Combolist",
    "author": "Megatron",
    "link": "https://breachforums.jp/Thread-120K-Bulgaria-HQ-Good-Combolist",
    "detection-date": "2026-02-05T21:47:16.237Z",
    "timestamp": "2026-02-05T21:47:16.237Z",
    "thread-id": "Thread-120K-Bulgaria-HQ-Good-Combolist",
    "link-hash": "27361a05eee0483e5b66a45fcb9f427bfc217c0f4849b51e81ac45556882d736"
  },
  {
    "name": "darkforums-database",
    "source": "https://darkforums.me/Forum-Databases?sortby=started\u0026order=desc\u0026datecut=9999\u0026prefix=0",
    "title": "[FR] ADMR (Aide à domicile en milieu rural)",
    "author": "RavenSec",
    "link": "https://darkforums.me/Thread-FR-ADMR-Aide-%C3%A0-domicile-en-milieu-rural",
    "detection-date": "2026-02-05T21:47:20.619Z",
    "timestamp": "2026-02-05T21:47:20.619Z",
    "thread-id": "Thread-FR-ADMR-Aide-%C3%A0-domicile-en-milieu-rural",
    "link-hash": "156bc6c05fc67d632cd69b0b3dc00ab355419e2d80bbbe26bcb88ffc2ddd93d0"
  },
  {
    "name": "darkforums-stealer-logs",
    "source": "https://darkforums.me/Forum-Stealer-Logs?sortby=started\u0026order=desc\u0026datecut=9999\u0026prefix=0",
    "title": "🚀 [5454 LOGS CLOUD] ☁ 05 FEBRUARY ❤️ FRESH LOGS❗️",
    "author": "UP_DAISYCLOUD",
    "link": "https://darkforums.me/Thread-%F0%9F%9A%80-5454-LOGS-CLOUD-%E2%98%81-05-FEBRUARY-%E2%9D%A4%EF%B8%8F-FRESH-LOGS%E2%9D%97%EF%B8%8F",
    "detection-date": "2026-02-05T21:47:22.492Z",
    "timestamp": "2026-02-05T21:47:22.492Z",
    "thread-id": "",
    "link-hash": "220e241843a9279655670a186a453bf664303eb2890fff4ccffbaa1faac60d06"
  },
  {
    "name": "htdark-combolist",
    "source": "https://htdark.com/forums/proxy-lists-combolists.189/",
    "title": "4.7K Fresh Mail Access Mix By MegaCloud 05.02",
    "author": "MailAccess",
    "link": "https://htdark.com/threads/4-7k-fresh-mail-access-mix-by-megacloud-05-02.141101/",
    "detection-date": "2026-02-05T21:47:22.623Z",
    "timestamp": "2026-02-05T21:47:22.623Z",
    "thread-id": "4",
    "link-hash": "a44422afbaf9390e6c3a361ebce616d2190a271047fbc83124cb848ee534f400"
  },
  {
    "name": "patched-accounts",
    "source": "https://patched.to/Forum-accounts?sortby=started\u0026order=desc\u0026datecut=9999\u0026prefix=0",
    "title": "Apple Music 3 months",
    "author": "Fireflame",
    "link": "https://patched.to/Thread-apple-music-3-months",
    "detection-date": "2026-02-05T21:47:23.435Z",
    "timestamp": "2026-02-05T21:47:23.435Z",
    "thread-id": "Thread-apple-music-3-months",
    "link-hash": "07431f72ea7be532750d7f5cca525beafb3ac9224d58f89b99dbd2c3ffd0251b"
  },
  {
    "name": "patched-combolist",
    "source": "https://patched.to/Forum-combolist?sortby=started\u0026order=desc\u0026datecut=9999\u0026prefix=0",
    "title": "✴️ 9.5K+ HQ Fresh Hotmails ✴️ Dropped In Private Channel 24H AGO 🔥🔥",
    "author": "Pirate999",
    "link": "https://patched.to/Thread-file-upload-%E2%9C%B4%EF%B8%8F-9-5k-hq-fresh-hotmails-%E2%9C%B4%EF%B8%8F-dropped-in-private-channel-24h-ago-%F0%9F%94%A5%F0%9F%94%A5",
    "detection-date": "2026-02-05T21:47:25.437Z",
    "timestamp": "2026-02-05T21:47:25.437Z",
    "thread-id": "",
    "link-hash": "41716e365165a98dc834f8f07d32a1607148e97c11cf2dcd0a7c60528bfecbd3"
  },
  {
    "name": "nulledbb-cracking",
    "source": "https://nulledbb.com/forum-Cracking-Proxies-and-Wordlists?sortby=started\u0026order=desc\u0026datecut=9999\u0026prefix=0",
    "title": "⚡⚡ 3659x PREMIUM MIX MAIL HITS⚡⚡",
    "author": "Xdalpha",
    "link": "https://nulledbb.com/thread-%E2%9A%A1%E2%9A%A1-3659x-PREMIUM-MIX-MAIL-HITS%E2%9A%A1%E2%9A%A1",
    "detection-date": "2026-02-05T21:47:27.608Z",
    "timestamp": "2026-02-05T21:47:27.608Z",
    "thread-id": "thread-%E2%9A%A1%E2%9A%A1-3659x-PREMIUM-MIX-MAIL-HITS%E2%9A%A1%E2%9A%A1",
    "link-hash": "e5b49db92b792d946974093f66dd80ca19a1a5cdcee587818cb3191e21946340"
  },
  {
    "name": "darkforums-stealer-logs",
    "source": "https://darkforums.me/Forum-Stealer-Logs?sortby=started\u0026order=desc\u0026datecut=9999\u0026prefix=0",
    "title": "Thread",
    "author": "",
    "link": "https://darkforums.me/Forum-Stealer-Logs?datecut=9999\u0026prefix=0\u0026sortby=subject\u0026order=asc",
    "detection-date": "2026-02-05T22:13:42.899Z",
    "timestamp": "2026-02-05T22:13:42.899Z",
    "thread-id": "Forum-Stealer-Logs",
    "link-hash": "cc7e5a88bbd34b224fa92c15d76eda5fa6cf0bb008368c926bf96ca71cab0b25"
  },
  {
    "name": "darkforums-combolists",
    "source": "https://darkforums.me/Forum-Combolists?sortby=started\u0026order=desc\u0026datecut=9999\u0026prefix=0",
    "title": "Thread",
    "author": "",
    "link": "https://darkforums.me/Forum-Combolists?datecut=9999\u0026prefix=0\u0026sortby=subject\u0026order=asc",
    "detection-date": "2026-02-05T22:13:43.244Z",
    "timestamp": "2026-02-05T22:13:43.244Z",
    "thread-id": "Forum-Combolists",
    "link-hash": "5d4909b4fc15367cf82b421580680b0a5bf7104aca8fa44d5ce8886cf067684e"
  },
  {
    "name": "patched-combolist",
    "source": "https://patched.to/Forum-combolist?sortby=started\u0026order=desc\u0026datecut=9999\u0026prefix=0",
    "title": "7 k HQ HOTMAIL Access VALID/HIT (Fresh)",
    "author": "NullShop",
    "link": "https://patched.to/Thread-file-upload-7%C2%A0k-hq-hotmail-access-valid-hit-fresh",
    "detection-date": "2026-02-05T22:13:45.551Z",
    "timestamp": "2026-02-05T22:13:45.551Z",
    "thread-id": "Thread-file-upload-7%C2%A0k-hq-hotmail-access-valid-hit-fresh",
    "link-hash": "be2790435f9a8179f4677e59f7e1160507b589482d0529195a9c345e33beef11"
  },
  {
    "name": "darkforums-other-leaks",
    "source": "https://darkforums.me/Forum-Other-Leaks?sortby=started\u0026order=desc\u0026datecut=9999\u0026prefix=0",
    "title": "Thread",
    "author": "",
    "link": "https://darkforums.me/Forum-Other-Leaks?datecut=9999\u0026prefix=0\u0026sortby=subject\u0026order=asc",
    "detection-date": "2026-02-05T22:13:48.991Z",
    "timestamp": "2026-02-05T22:13:48.991Z",
    "thread-id": "Forum-Other-Leaks",
    "link-hash": "bae9f24fe47a3aa2d974bd3441d43282d37f0b53e152dcb2c6262975327cf7d0"
  },
  {
    "name": "ransomhouse",
    "source": "http://rnsm777cdsjrsdlbs4v5qoeppu3px6sb2igmh53jzrx7ipcrbjz5b2ad.onion/",
    "title": "ADDA (adda.io)",
    "author": "",
    "link": "http://rnsm777cdsjrsdlbs4v5qoeppu3px6sb2igmh53jzrx7ipcrbjz5b2ad.onion/2025/03/07/adda-io-software/",
    "detection-date": "2026-02-05T22:13:52.721Z",
    "timestamp": "2026-02-05T22:13:52.721Z",
    "thread-id": "adda-io-software",
    "link-hash": "9f33210aea850e8f9fb27714a21e45a5497577595ed57f4dedef60cbb5621abc"
  },
  {
    "name": "breachforums-database",
    "source": "https://breachforums.jp/Forum-Databases?sortby=started\u0026order=desc\u0026datecut=9999\u0026prefix=0",
    "title": "jplatform.am 354k ARMANIA PERSON NUMBER",
    "author": "azrekx",
    "link": "https://breachforums.jp/Thread-DATABASE-jplatform-am-354k-ARMANIA-PERSON-NUMBER",
    "detection-date": "2026-02-05T22:24:02.718Z",
    "timestamp": "2026-02-05T22:24:02.718Z",
    "thread-id": "Thread-DATABASE-jplatform-am-354k-ARMANIA-PERSON-NUMBER",
    "link-hash": "9c451b3fb064b07f6252017f2fa854ebbebac69b22566c5bde876bb6f9025313"
  },
  {
    "name": "nulledbb-cracking",
    "source": "https://nulledbb.com/forum-Cracking-Proxies-and-Wordlists?sortby=started\u0026order=desc\u0026datecut=9999\u0026prefix=0",
    "title": "4.6K Hotmail Freesh Mail Access by MegaCloud 05.02",
    "author": "MegaCloud",
    "link": "https://nulledbb.com/thread-4-6K-Hotmail-Freesh-Mail-Access-by-MegaCloud-05-02",
    "detection-date": "2026-02-05T22:24:10.845Z",
    "timestamp": "2026-02-05T22:24:10.845Z",
    "thread-id": "4",
    "link-hash": "0624b943bd59dae126cdba3b07c211d22609cb9a7edbaa69f48f4618d540cb43"
  },
  {
    "name": "ransomhouse",
    "source": "http://rnsm777cdsjrsdlbs4v5qoeppu3px6sb2igmh53jzrx7ipcrbjz5b2ad.onion/",
    "title": "ADDA (adda.io)",
    "author": "ransomhouse",
    "link": "http://rnsm777cdsjrsdlbs4v5qoeppu3px6sb2igmh53jzrx7ipcrbjz5b2ad.onion/2025/03/07/adda-io-software/",
    "detection-date": "2026-02-05T22:24:18.917Z",
    "timestamp": "2026-02-05T22:24:18.917Z",
    "thread-id": "adda-io-software",
    "link-hash": "9f33210aea850e8f9fb27714a21e45a5497577595ed57f4dedef60cbb5621abc"
  },
  {
    "name": "breachforums-database",
    "source": "https://breachforums.jp/Forum-Databases?sortby=started\u0026order=desc\u0026datecut=9999\u0026prefix=0",
    "title": "jplatform.am 354k ARMANIA PERSON NUMBER",
    "author": "azrekx",
    "link": "https://breachforums.jp/Thread-DATABASE-jplatform-am-354k-ARMANIA-PERSON-NUMBER",
    "detection-date": "2026-02-05T22:35:23.756Z",
    "timestamp": "2026-02-05T22:35:23.756Z",
    "thread-id": "Thread-DATABASE-jplatform-am-354k-ARMANIA-PERSON-NUMBER",
    "link-hash": "9c451b3fb064b07f6252017f2fa854ebbebac69b22566c5bde876bb6f9025313"
  },
  {
    "name": "nulledbb-cracking",
    "source": "https://nulledbb.com/forum-Cracking-Proxies-and-Wordlists?sortby=started\u0026order=desc\u0026datecut=9999\u0026prefix=0",
    "title": "160k Fresh HQ Combolist Email-Pass [Netflix,Minecraft,Uplay,Steam,Hulu,spotify]",
    "author": "Harry01",
    "link": "https://nulledbb.com/thread-160k-Fresh-HQ-Combolist-Email-Pass-Netflix-Minecraft-Uplay-Steam-Hulu-spotify--2282627",
    "detection-date": "2026-02-05T22:35:32.018Z",
    "timestamp": "2026-02-05T22:35:32.018Z",
    "thread-id": "160",
    "link-hash": "129774c7f3764cfd267754e6ea7f391a75df9cb05b0262a3462e43b302eae214"
  },
  {
    "name": "ransomhouse",
    "source": "http://rnsm777cdsjrsdlbs4v5qoeppu3px6sb2igmh53jzrx7ipcrbjz5b2ad.onion/",
    "title": "ADDA (adda.io)",
    "author": "RansomHouse",
    "link": "http://rnsm777cdsjrsdlbs4v5qoeppu3px6sb2igmh53jzrx7ipcrbjz5b2ad.onion/2025/03/07/adda-io-software/",
    "description": "ADDA is SaaS for Residential Community Management. 12 millions residents, visitors and stuff records leaked.",
    "detection-date": "2026-02-05T22:35:45.354Z",
    "timestamp": "2026-02-05T22:35:45.354Z",
    "thread-id": "adda-io-software",
    "link-hash": "9f33210aea850e8f9fb27714a21e45a5497577595ed57f4dedef60cbb5621abc"
  },
  {
    "name": "darkforums-database",
    "source": "https://darkforums.me/Forum-Databases?sortby=started\u0026order=desc\u0026datecut=9999\u0026prefix=0",
    "title": "Thread",
    "author": "",
    "link": "https://darkforums.me/Forum-Databases?datecut=9999\u0026prefix=0\u0026sortby=subject\u0026order=asc",
    "detection-date": "2026-02-05T22:57:23.788Z",
    "timestamp": "2026-02-05T22:57:23.788Z",
    "thread-id": "Forum-Databases",
    "link-hash": "64220aa39eba323f12e5a19364167edb8f7ecd72faa859eb5e239ef09f984d4a"
  },
  {
    "name": "patched-combolist",
    "source": "https://patched.to/Forum-combolist?sortby=started\u0026order=desc\u0026datecut=9999\u0026prefix=0",
    "title": "3034 Hotmail Full Hits",
    "author": "RAndomuser224",
    "link": "https://patched.to/Thread-file-upload-3034-hotmail-full-hits",
    "detection-date": "2026-02-05T22:57:27.469Z",
    "timestamp": "2026-02-05T22:57:27.469Z",
    "thread-id": "Thread-file-upload-3034-hotmail-full-hits",
    "link-hash": "4e538efd0f5a7aba926e65ad78897a08bcd2e6570c6d6e650571b4506f48d7fe"
  },
  {
    "name": "darkweb-vc",
    "source": "https://darkweb.vc/darkweb",
    "title": "「 593K 」⭐️CHESS.COM COMBOLIST⭐️ GOOD QUALITY ⭐️100% PRIVATE ⭐️FRESHLY DUMPED⭐️ | Cracked.sh",
    "author": "",
    "link": "https://darkweb.vc/details/Q0tLQ0EQQ0VFRRFGFkAXERYRFkFDREERRBUXFUFFQUdZAwYRHRYHXhsHHh9eQ0NDQ0BC",
    "detection-date": "2026-02-05T22:57:37.079Z",
    "timestamp": "2026-02-05T22:57:37.079Z",
    "thread-id": "Q0tLQ0EQQ0VFRRFGFkAXERYRFkFDREERRBUXFUFFQUdZAwYRHRYHXhsHHh9eQ0NDQ0BC",
    "link-hash": "b64371d148e7423d1fba8d56b9eedf33eae1fa364fffc291f57153cfd64c4191"
  },
  {
    "name": "darkweb-vc",
    "source": "https://darkweb.vc/darkweb",
    "title": "「 593K 」⭐️CHESS.COM COMBOLIST⭐️ GOOD QUALITY ⭐️100% PRIVATE ⭐️FRESHLY DUMPED⭐️ | Cracked.sh",
    "author": "MetaCloud3",
    "link": "https://darkweb.vc/details/Q0tLQ0EQQ0VFRRFGFkAXERYRFkFDREERRBUXFUFFQUdZAwYRHRYHXhsHHh9eQ0NDQ0BC",
    "detection-date": "2026-02-05T23:01:42.834Z",
    "timestamp": "2026-02-05T23:01:42.834Z",
    "thread-id": "Q0tLQ0EQQ0VFRRFGFkAXERYRFkFDREERRBUXFUFFQUdZAwYRHRYHXhsHHh9eQ0NDQ0BC",
    "link-hash": "b64371d148e7423d1fba8d56b9eedf33eae1fa364fffc291f57153cfd64c4191"
  }
]